[{"place_id": 396106837, "licence": "Data \u00a9 OpenStreetMap contributors, ODbL 1.0. http://osm.org/copyright", "osm_type": "node", "osm_id": 158854291, "lat": "40.6667702", "lon": "-73.8823583", "class": "place", "type": "suburb", "place_rank": 19, "importance": 0.42033767099547437, "addresstype": "suburb", "name": "East New York", "display_name": "East New York, Brooklyn, Kings County, New York, 11208, United States", "boundingbox": ["40.6467702", "40.6867702", "-73.9023583", "-73.8623583"], "geojson": {"type": "Point", "coordinates": [-73.8823583, 40.6667702]}}, {"place_id": 332077918, "licence": "Data \u00a9 OpenStreetMap contributors, ODbL 1.0. http://osm.org/copyright", "osm_type": "node", "osm_id": 597828361, "lat": "40.6758826", "lon": "-73.9032829", "class": "railway", "type": "station", "place_rank": 30, "importance": 0.35182458214669665, "addresstype": "railway", "name": "East New York", "display_name": "East New York, Atlantic Avenue, Broadway Junction, Brooklyn, Kings County, New York, 11207, United States", "boundingbox": ["40.6708826", "40.6808826", "-73.9082829", "-73.8982829"], "geojson": {"type": "Point", "coordinates": [-73.9032829, 40.6758826]}}]