[{"place_id": 331230011, "licence": "Data \u00a9 OpenStreetMap contributors, ODbL 1.0. http://osm.org/copyright", "osm_type": "node", "osm_id": 158842637, "lat": "40.6875470", "lon": "-73.9973352", "class": "place", "type": "neighbourhood", "place_rank": 20, "importance": 0.36316812342016486, "addresstype": "neighbourhood", "name": "Cobble Hill", "display_name": "Cobble Hill, Brooklyn, Kings County, New York, 11201, United States", "boundingbox": ["40.6775470", "40.6975470", "-74.0073352", "-73.9873352"], "geojson": {"type": "Point", "coordinates": [-73.9973352, 40.687547]}}, {"place_id": 337998234, "licence": "Data \u00a9 OpenStreetMap contributors, ODbL 1.0. http://osm.org/copyright", "osm_type": "node", "osm_id": 357554436, "lat": "44.2031057", "lon": "-73.6215223", "class": "natural", "type": "peak", "place_rank": 18, "importance": 0.16005132143129625, "addresstype": "peak", "name": "Cobble Hill", "display_name": "Cobble Hill, Essex County, New York, 12932, United States", "boundingbox": ["44.2030557", "44.2031557", "-73.6215723", "-73.6214723"], "geojson": {"type": "Point", "coordinates": [-73.6215223, 44.2031057]}}, {"place_id": 334104589, "licence": "Data \u00a9 OpenStreetMap contributors, ODbL 1.0. http://osm.org/copyright", "osm_type": "node", "osm_id": 357554406, "lat": "43.8600622", "lon": "-73.9056908", "class": "natural", "type": "peak", "place_rank": 18, "importance": 0.16005000152590218, "addresstype": "peak", "name": "Cobble Hill", "display_name": "Cobble Hill, Town of Schroon, Essex County, New York, United States", "boundingbox": ["43.8600122", "43.8601122", "-73.9057408", "-73.9056408"], "geojson": {"type": "Point", "coordinates": [-73.9056908, 43.8600622]}}, {"place_id": 337897570, "licence": "Data \u00a9 OpenStreetMap contributors, ODbL 1.0. http://osm.org/copyright", "osm_type": "node", "osm_id": 357554415, "lat": "44.2931024", "lon": "-73.9626483", "class": "natural", "type": "peak", "place_rank": 18, "importance": 0.16004961852445257, "addresstype": "peak", "name": "Cobble Hill", "display_name": "Cobble Hill, Town of North Elba, Essex County, New York, 12946, United States", "boundingbox": ["44.2930524", "44.2931524", "-73.9626983", "-73.9625983"], "geojson": {"type": "Point", "coordinates": [-73.9626483, 44.2931024]}}, {"place_id": 326050461, "licence": "Data \u00a9 OpenStreetMap contributors, ODbL 1.0. http://osm.org/copyright", "osm_type": "node", "osm_id": 357554399, "lat": "43.6203448", "lon": "-74.5571019", "class": "natural", "type": "peak", "place_rank": 18, "importance": 0.16003700846875712, "addresstype": "peak", "name": "Cobble Hill", "display_name": "Cobble Hill, Hamilton County, New York, United States", "boundingbox": ["43.6202948", "43.6203948", "-74.5571519", "-74.5570519"], "geojson": {"type": "Point", "coordinates": [-74.5571019, 43.6203448]}}, {"place_id": 322656534, "licence": "Data \u00a9 OpenStreetMap contributors, ODbL 1.0. http://osm.org/copyright", "osm_type": "node", "osm_id": 357554392, "lat": "42.7720047", "lon": "-78.2872377", "class": "natural", "type": "peak", "place_rank": 18, "importance": 0.16003627298390172, "addresstype": "peak", "name": "Cobble Hill", "display_name": "Cobble Hill, Town of Orangeville, Wyoming County, New York, 14167, United States", "boundingbox": ["42.7719547", "42.7720547", "-78.2872877", "-78.2871877"], "geojson": {"type": "Point", "coordinates": [-78.2872377, 42.7720047]}}]